har_dl/__init__.py
har_dl/__main__.py
har_dl/downloader.py
har_dl/harfile.py
har_dl-0.1.1.dist-info/LICENSE
har_dl-0.1.1.dist-info/METADATA
har_dl-0.1.1.dist-info/WHEEL
har_dl-0.1.1.dist-info/entry_points.txt
har_dl-0.1.1.dist-info/top_level.txt
har_dl-0.1.1.dist-info/RECORD
