Metadata-Version: 2.1
Name: har-dl
Version: 0.1.1
Summary: Utility for downloading content from .HAR files
Home-page: https://github.com/docyx/har-dl
Author: docyx
License: UNKNOWN
Platform: UNKNOWN
Classifier: Programming Language :: Python :: 3
Classifier: License :: OSI Approved :: MIT License
Classifier: Operating System :: OS Independent
Classifier: Environment :: Console
Classifier: Topic :: Internet
Classifier: Topic :: Internet :: WWW/HTTP
Requires-Python: >=3.6
Requires-Dist: tqdm
